[
    {
        "edges": [["A", "B"]],
        "vertexes": {"A": 20, "B": 10}
    },
    {
        "edges": [["A", "B"], ["B", "C"]],
        "vertexes": {"A": 10, "B": 10, "C": 10}
    },
    {
        "edges": [["A", "B"], ["C", "B"], ["D", "C"], ["D", "E"], ["E", "F"] ],
        "vertexes": {"A": 20, "B": 10, "C": 20, "D": 10, "E": 20, "F": 10}
    },
    {
        "edges": [["A", "B"], ["C", "B"], ["D", "C"]],
        "vertexes": {"A": 10, "B": 20, "C": 10, "D": 20}
    },
    {
        "edges": [["A", "B"], ["C", "B"], ["D", "B"], ["E", "B"], ["F", "E"], ["F", "A"]],
        "vertexes": {"A": 2, "B": 1, "C": 1, "D": 2, "E": 1, "F": 4}
    }
]